nonebot_plugin_asmr100/__init__.py
nonebot_plugin_asmr100/config.py
nonebot_plugin_asmr100/data_source.py
nonebot_plugin_asmr100/file_handler.py
nonebot_plugin_asmr100/states.py
nonebot_plugin_asmr100/utils.py
nonebot_plugin_asmr100/__pycache__/__init__.cpython-313.pyc
nonebot_plugin_asmr100/__pycache__/config.cpython-313.pyc
nonebot_plugin_asmr100/__pycache__/data_source.cpython-313.pyc
nonebot_plugin_asmr100/__pycache__/file_handler.cpython-313.pyc
nonebot_plugin_asmr100/__pycache__/utils.cpython-313.pyc
nonebot_plugin_asmr100/commands/__init__.py
nonebot_plugin_asmr100/commands/play.py
nonebot_plugin_asmr100/commands/search.py
nonebot_plugin_asmr100/commands/__pycache__/play.cpython-313.pyc
nonebot_plugin_asmr100-0.3.1.dist-info/METADATA
nonebot_plugin_asmr100-0.3.1.dist-info/WHEEL
nonebot_plugin_asmr100-0.3.1.dist-info/top_level.txt
nonebot_plugin_asmr100-0.3.1.dist-info/RECORD
